[
  {
    "source": "K-Startup",
    "title": "사업신청관리",
    "region": "중앙",
    "target": "청년/예비창업/창업",
    "industry": "",
    "budget": "",
    "benefit_type": "지원사업",
    "deadline": "",
    "link": "https://www.k-startup.go.kr/passni/kstartup/tokenInfoRelay.jsp?flag=biz",
    "summary": "",
    "keywords": ""
  },
  {
    "source": "K-Startup",
    "title": "중소벤처24\n                        증명서 및 사업신청 통화서비스 제공",
    "region": "중앙",
    "target": "청년/예비창업/창업",
    "industry": "",
    "budget": "",
    "benefit_type": "지원사업",
    "deadline": "",
    "link": "https://www.k-startup.go.kr/magicsso/requestAuthEx.jsp?RelayState=https://www.smes.go.kr/main/magicsso/requestConnect.jsp",
    "summary": "",
    "keywords": ""
  },
  {
    "source": "K-Startup",
    "title": "소상공인지식배움터\n                        소상공인 단계별 맞춤형 교육 제공",
    "region": "중앙",
    "target": "청년/예비창업/창업",
    "industry": "",
    "budget": "",
    "benefit_type": "지원사업",
    "deadline": "",
    "link": "https://www.k-startup.go.kr/magicsso/requestAuthEx.jsp?RelayState=https://sso.sbiz.or.kr/magicsso/requestConnect.jsp?RelayState=/sso/agentLoginAction.do?reqSite=edu",
    "summary": "",
    "keywords": ""
  },
  {
    "source": "K-Startup",
    "title": "기술보호울타리\n                        기술보호 정부사업 정보 제공",
    "region": "중앙",
    "target": "청년/예비창업/창업",
    "industry": "",
    "budget": "",
    "benefit_type": "지원사업",
    "deadline": "",
    "link": "https://www.k-startup.go.kr/magicsso/requestAuthEx.jsp?RelayState=https://www.ultari.go.kr/magicsso/requestConnect.jsp",
    "summary": "",
    "keywords": ""
  },
  {
    "source": "K-Startup",
    "title": "기업마당\n                        중소기업 지원정책 정보 제공",
    "region": "중앙",
    "target": "청년/예비창업/창업",
    "industry": "",
    "budget": "",
    "benefit_type": "지원사업",
    "deadline": "",
    "link": "https://www.k-startup.go.kr/magicsso/requestAuthEx.jsp?RelayState=https://www.bizinfo.go.kr/magicsso/requestConnect.jsp",
    "summary": "",
    "keywords": ""
  },
  {
    "source": "K-Startup",
    "title": "산학연플러스\n                        산학연 협력 정보 제공",
    "region": "중앙",
    "target": "청년/예비창업/창업",
    "industry": "",
    "budget": "",
    "benefit_type": "지원사업",
    "deadline": "",
    "link": "https://www.k-startup.go.kr/magicsso/requestAuthEx.jsp?RelayState=https://plus.auri.go.kr/magicsso/requestConnect.jsp",
    "summary": "",
    "keywords": ""
  },
  {
    "source": "K-Startup",
    "title": "상권정보시스템\n                        업종별 상권분석 정보 제공",
    "region": "중앙",
    "target": "청년/예비창업/창업",
    "industry": "",
    "budget": "",
    "benefit_type": "지원사업",
    "deadline": "",
    "link": "https://www.k-startup.go.kr/magicsso/requestAuthEx.jsp?RelayState=https://sso.sbiz.or.kr/magicsso/requestConnect.jsp?RelayState=/sso/agentLoginAction.do?reqSite=sg",
    "summary": "",
    "keywords": ""
  },
  {
    "source": "K-Startup",
    "title": "소상공인마당\n                        창업 및 운영 정보 제공",
    "region": "중앙",
    "target": "청년/예비창업/창업",
    "industry": "",
    "budget": "",
    "benefit_type": "지원사업",
    "deadline": "",
    "link": "https://www.k-startup.go.kr/magicsso/requestAuthEx.jsp?RelayState=https://sso.sbiz.or.kr/magicsso/requestConnect.jsp?RelayState=/sso/agentLoginAction.do?reqSite=sbiz",
    "summary": "",
    "keywords": ""
  },
  {
    "source": "K-Startup",
    "title": "스마트공장사업관리시스템\n                        스마트공장 시스템 사업 정보 제공",
    "region": "중앙",
    "target": "청년/예비창업/창업",
    "industry": "",
    "budget": "",
    "benefit_type": "지원사업",
    "deadline": "",
    "link": "https://www.k-startup.go.kr/magicsso/requestAuthEx.jsp?RelayState=https://www.smart-factory.kr/magicsso/requestConnect.jsp",
    "summary": "",
    "keywords": ""
  },
  {
    "source": "K-Startup",
    "title": "중소기업 기술개발사업 종합관리시스템\n                        기술개발지원사업 정보 제공",
    "region": "중앙",
    "target": "청년/예비창업/창업",
    "industry": "",
    "budget": "",
    "benefit_type": "지원사업",
    "deadline": "",
    "link": "https://www.k-startup.go.kr/magicsso/requestAuthEx.jsp?RelayState=https://www.smtech.go.kr/front/magicsso/requestConnect.jsp",
    "summary": "",
    "keywords": ""
  },
  {
    "source": "K-Startup",
    "title": "중소기업 인력지원사업 종합관리시스템\n                        인력 지원사업 정보 제공",
    "region": "중앙",
    "target": "청년/예비창업/창업",
    "industry": "",
    "budget": "",
    "benefit_type": "지원사업",
    "deadline": "",
    "link": "https://www.k-startup.go.kr/magicsso/requestAuthEx.jsp?RelayState=https://www.smes.go.kr/sanhakin/magicsso/requestConnect.jsp?RelayState=/sanhakin/connApi/connClient.jsp",
    "summary": "",
    "keywords": ""
  },
  {
    "source": "K-Startup",
    "title": "중소기업현황정보시스템\n                        중소기업확인서 신청 및 발급 제공",
    "region": "중앙",
    "target": "청년/예비창업/창업",
    "industry": "",
    "budget": "",
    "benefit_type": "지원사업",
    "deadline": "",
    "link": "https://www.k-startup.go.kr/magicsso/requestAuthEx.jsp?RelayState=https://sminfo.mss.go.kr/magicsso/requestConnect.jsp",
    "summary": "",
    "keywords": ""
  },
  {
    "source": "K-Startup",
    "title": "중소벤처기업진흥공단\n                        기업 자금 운영지원 정보 제공",
    "region": "중앙",
    "target": "청년/예비창업/창업",
    "industry": "",
    "budget": "",
    "benefit_type": "지원사업",
    "deadline": "",
    "link": "https://www.k-startup.go.kr/magicsso/requestAuthEx.jsp?RelayState=https://www.kosmes.or.kr/magicsso/requestConnect.jsp",
    "summary": "",
    "keywords": ""
  },
  {
    "source": "K-Startup",
    "title": "창업보육센터 네트워크시스템\n                        창업지원 종합정보 제공",
    "region": "중앙",
    "target": "청년/예비창업/창업",
    "industry": "",
    "budget": "",
    "benefit_type": "지원사업",
    "deadline": "",
    "link": "https://www.k-startup.go.kr/magicsso/requestAuthEx.jsp?RelayState=https://www.smes.go.kr/binet/magicsso/requestConnect.jsp?RelayState=https://www.smes.go.kr/binet/connApi/connClient.jsp",
    "summary": "",
    "keywords": ""
  },
  {
    "source": "K-Startup",
    "title": "창업기업 확인시스템\n                        창업기업 확인시스템",
    "region": "중앙",
    "target": "청년/예비창업/창업",
    "industry": "",
    "budget": "",
    "benefit_type": "지원사업",
    "deadline": "",
    "link": "https://www.k-startup.go.kr/magicsso/requestAuthEx.jsp?RelayState=https://cert.k-startup.go.kr/magicsso/requestConnect.jsp?RelayState=/uat/uia/ssoLoginByCi.do",
    "summary": "",
    "keywords": ""
  },
  {
    "source": "K-Startup",
    "title": "2025년 판교 경기문화창조허브 스타트업 오피스 신규 입주기업(16기 3분기) 모집\n\t\t\t\t\t\t\t\t\t\t\t\t\t\t\t\t새로운게시글",
    "region": "중앙",
    "target": "청년/예비창업/창업",
    "industry": "",
    "budget": "",
    "benefit_type": "지원사업",
    "deadline": "",
    "link": "javascript:go_view(175380);",
    "summary": "",
    "keywords": ""
  },
  {
    "source": "K-Startup",
    "title": "2026년 글로벌 기업 협업 프로그램(Around X) 지원사업 신규 주관기관 모집 공고\n\t\t\t\t\t\t\t\t\t\t\t\t\t\t\t\t새로운게시글",
    "region": "중앙",
    "target": "청년/예비창업/창업",
    "industry": "",
    "budget": "",
    "benefit_type": "지원사업",
    "deadline": "",
    "link": "javascript:go_view(175495);",
    "summary": "",
    "keywords": ""
  },
  {
    "source": "K-Startup",
    "title": "[소담스퀘어 당산] 윤자동과 함께하는 MAKE 실무 자동화 커리큘럼 교육\n\t\t\t\t\t\t\t\t\t\t\t\t\t\t\t\t새로운게시글",
    "region": "중앙",
    "target": "청년/예비창업/창업",
    "industry": "",
    "budget": "",
    "benefit_type": "지원사업",
    "deadline": "",
    "link": "javascript:go_view(175475);",
    "summary": "",
    "keywords": ""
  },
  {
    "source": "K-Startup",
    "title": "2025년 한국항공대학교 창업보육센터 입주기업 모집\n\t\t\t\t\t\t\t\t\t\t\t\t\t\t\t\t새로운게시글",
    "region": "중앙",
    "target": "청년/예비창업/창업",
    "industry": "",
    "budget": "",
    "benefit_type": "지원사업",
    "deadline": "",
    "link": "javascript:go_view(175457);",
    "summary": "",
    "keywords": ""
  },
  {
    "source": "K-Startup",
    "title": "2025 웰컴 투 팁스 대경권 네트워킹 모집\n\t\t\t\t\t\t\t\t\t\t\t\t\t\t\t\t새로운게시글",
    "region": "중앙",
    "target": "청년/예비창업/창업",
    "industry": "",
    "budget": "",
    "benefit_type": "지원사업",
    "deadline": "",
    "link": "javascript:go_view(175486);",
    "summary": "",
    "keywords": ""
  },
  {
    "source": "K-Startup",
    "title": "[무료/초기 창업자 집중] 2025년 대구 블록체인 밋업데이 - 블록체인·스마트컨트랙트 보안위협 분석 및 대응\n\t\t\t\t\t\t\t\t\t\t\t\t\t\t\t\t새로운게시글",
    "region": "중앙",
    "target": "청년/예비창업/창업",
    "industry": "",
    "budget": "",
    "benefit_type": "지원사업",
    "deadline": "",
    "link": "javascript:go_view(175476);",
    "summary": "",
    "keywords": ""
  },
  {
    "source": "K-Startup",
    "title": "2025 패션 관련 기업 대상  투자유치 전략 세미나\n\t\t\t\t\t\t\t\t\t\t\t\t\t\t\t\t새로운게시글",
    "region": "중앙",
    "target": "청년/예비창업/창업",
    "industry": "",
    "budget": "",
    "benefit_type": "지원사업",
    "deadline": "",
    "link": "javascript:go_view(175470);",
    "summary": "",
    "keywords": ""
  },
  {
    "source": "K-Startup",
    "title": "대전 (재)창업자 피보팅 지원 프로그램 모집 공고\n\t\t\t\t\t\t\t\t\t\t\t\t\t\t\t\t새로운게시글",
    "region": "중앙",
    "target": "청년/예비창업/창업",
    "industry": "",
    "budget": "",
    "benefit_type": "지원사업",
    "deadline": "",
    "link": "javascript:go_view(175485);",
    "summary": "",
    "keywords": ""
  },
  {
    "source": "K-Startup",
    "title": "인공지능산업융합사업단「AI 창업동」입주기업 모집 공고\n\t\t\t\t\t\t\t\t\t\t\t\t\t\t\t\t새로운게시글",
    "region": "중앙",
    "target": "청년/예비창업/창업",
    "industry": "",
    "budget": "",
    "benefit_type": "지원사업",
    "deadline": "",
    "link": "javascript:go_view(175488);",
    "summary": "",
    "keywords": ""
  },
  {
    "source": "K-Startup",
    "title": "2025년 금천구 G밸리 ESG 혁신기업 육성 지원사업 모집 공고 \n\t\t\t\t\t\t\t\t\t\t\t\t\t\t\t\t새로운게시글",
    "region": "중앙",
    "target": "청년/예비창업/창업",
    "industry": "",
    "budget": "",
    "benefit_type": "지원사업",
    "deadline": "",
    "link": "javascript:go_view(175489);",
    "summary": "",
    "keywords": ""
  },
  {
    "source": "K-Startup",
    "title": "2025년 하반기 창업성장센터 입주기업 추가 모집\n\t\t\t\t\t\t\t\t\t\t\t\t\t\t\t\t새로운게시글",
    "region": "중앙",
    "target": "청년/예비창업/창업",
    "industry": "",
    "budget": "",
    "benefit_type": "지원사업",
    "deadline": "",
    "link": "javascript:go_view(175478);",
    "summary": "",
    "keywords": ""
  },
  {
    "source": "K-Startup",
    "title": "[동작구 청년창업지원센터] 11월 정부지원사업, 사업계획서 전문가 컨설팅\n\t\t\t\t\t\t\t\t\t\t\t\t\t\t\t\t새로운게시글",
    "region": "중앙",
    "target": "청년/예비창업/창업",
    "industry": "",
    "budget": "",
    "benefit_type": "지원사업",
    "deadline": "",
    "link": "javascript:go_view(175492);",
    "summary": "",
    "keywords": ""
  },
  {
    "source": "K-Startup",
    "title": "2025년 한국외대 창업보육센터 입주기업 모집 공고\n\t\t\t\t\t\t\t\t\t\t\t\t\t\t\t\t새로운게시글",
    "region": "중앙",
    "target": "청년/예비창업/창업",
    "industry": "",
    "budget": "",
    "benefit_type": "지원사업",
    "deadline": "",
    "link": "javascript:go_view(175487);",
    "summary": "",
    "keywords": ""
  },
  {
    "source": "K-Startup",
    "title": "2025년 동아대학교 초기창업패키지 '아세안(베트남)진출 지원사업' 프로그램 모집공고",
    "region": "중앙",
    "target": "청년/예비창업/창업",
    "industry": "",
    "budget": "",
    "benefit_type": "지원사업",
    "deadline": "",
    "link": "javascript:go_view(175459);",
    "summary": "",
    "keywords": ""
  },
  {
    "source": "K-Startup",
    "title": "한남대학교 캠퍼스혁신파크 산학연혁신허브 입점자 모집 공고",
    "region": "중앙",
    "target": "청년/예비창업/창업",
    "industry": "",
    "budget": "",
    "benefit_type": "지원사업",
    "deadline": "",
    "link": "javascript:go_view(175465);",
    "summary": "",
    "keywords": ""
  },
  {
    "source": "기업마당",
    "title": "2026년 글로벌 기업 협업 프로그램(AroundX) 지원사업 신규 주관기관 모집 공고",
    "region": "2026년 글로벌 기업 협업 프로그램(AroundX) 지원사업 신규 주관기관 모집 공고",
    "target": "중소기업/청년",
    "industry": "",
    "budget": "",
    "benefit_type": "지원사업",
    "deadline": "중소벤처기업부",
    "link": "https://www.bizinfo.go.kr/view.do?pblancId=PBLN_000000000116160",
    "summary": "",
    "keywords": ""
  },
  {
    "source": "기업마당",
    "title": "2025년 방사선 기술 IP보증연계 지식재산평가 지원사업 공고",
    "region": "2025년 방사선 기술 IP보증연계 지식재산평가 지원사업 공고",
    "target": "중소기업/청년",
    "industry": "",
    "budget": "",
    "benefit_type": "지원사업",
    "deadline": "과학기술정보통신부",
    "link": "https://www.bizinfo.go.kr/view.do?pblancId=PBLN_000000000116180",
    "summary": "",
    "keywords": ""
  },
  {
    "source": "기업마당",
    "title": "[충북] 2025년 IP디딤돌 프로그램 후속지원 추가모집 공고",
    "region": "[충북] 2025년 IP디딤돌 프로그램 후속지원 추가모집 공고",
    "target": "중소기업/청년",
    "industry": "",
    "budget": "",
    "benefit_type": "지원사업",
    "deadline": "충청북도",
    "link": "https://www.bizinfo.go.kr/view.do?pblancId=PBLN_000000000116179",
    "summary": "",
    "keywords": ""
  },
  {
    "source": "기업마당",
    "title": "2025년 3차 수산물직매장 설치 및 창업지원플랫폼 구축 관련 수산물 직매장 창업희망자 지원 모집 연장 공고",
    "region": "2025년 3차 수산물직매장 설치 및 창업지원플랫폼 구축 관련 수산물 직매장 창업희망자 지원 모집 연장 공고",
    "target": "중소기업/청년",
    "industry": "",
    "budget": "",
    "benefit_type": "지원사업",
    "deadline": "해양수산부",
    "link": "https://www.bizinfo.go.kr/view.do?pblancId=PBLN_000000000116178",
    "summary": "",
    "keywords": ""
  },
  {
    "source": "기업마당",
    "title": "[인천] 2026년CES 혁신상 수상(2단계 쇼케이스) 지원사업 참가기업 모집 공고",
    "region": "[인천] 2026년CES 혁신상 수상(2단계 쇼케이스) 지원사업 참가기업 모집 공고",
    "target": "중소기업/청년",
    "industry": "",
    "budget": "",
    "benefit_type": "지원사업",
    "deadline": "인천광역시",
    "link": "https://www.bizinfo.go.kr/view.do?pblancId=PBLN_000000000116159",
    "summary": "",
    "keywords": ""
  },
  {
    "source": "기업마당",
    "title": "[인천] 동구 2025년 국내 전시회 참가기업 지원사업 추가 공고",
    "region": "[인천] 동구 2025년 국내 전시회 참가기업 지원사업 추가 공고",
    "target": "중소기업/청년",
    "industry": "",
    "budget": "",
    "benefit_type": "지원사업",
    "deadline": "인천광역시",
    "link": "https://www.bizinfo.go.kr/view.do?pblancId=PBLN_000000000116177",
    "summary": "",
    "keywords": ""
  },
  {
    "source": "기업마당",
    "title": "2026년 정보통신 및 정보문화 유공 정부포상 계획 공고",
    "region": "2026년 정보통신 및 정보문화 유공 정부포상 계획 공고",
    "target": "중소기업/청년",
    "industry": "",
    "budget": "",
    "benefit_type": "지원사업",
    "deadline": "과학기술정보통신부",
    "link": "https://www.bizinfo.go.kr/view.do?pblancId=PBLN_000000000116176",
    "summary": "",
    "keywords": ""
  },
  {
    "source": "기업마당",
    "title": "2025년 9차 정보보호 인증제품 조달청 벤처나라 추천기업 모집 공고(12월 지정심사)",
    "region": "2025년 9차 정보보호 인증제품 조달청 벤처나라 추천기업 모집 공고(12월 지정심사)",
    "target": "중소기업/청년",
    "industry": "",
    "budget": "",
    "benefit_type": "지원사업",
    "deadline": "과학기술정보통신부",
    "link": "https://www.bizinfo.go.kr/view.do?pblancId=PBLN_000000000116175",
    "summary": "",
    "keywords": ""
  },
  {
    "source": "기업마당",
    "title": "2025년 우수농식품신선도제고 지원사업 모집 공고",
    "region": "2025년 우수농식품신선도제고 지원사업 모집 공고",
    "target": "중소기업/청년",
    "industry": "",
    "budget": "",
    "benefit_type": "지원사업",
    "deadline": "농림축산식품부",
    "link": "https://www.bizinfo.go.kr/view.do?pblancId=PBLN_000000000116158",
    "summary": "",
    "keywords": ""
  },
  {
    "source": "기업마당",
    "title": "[경남] 창원시 2025년 수소산업 해외 교류 지원사업 참여기업 추가 모집 공고",
    "region": "[경남] 창원시 2025년 수소산업 해외 교류 지원사업 참여기업 추가 모집 공고",
    "target": "중소기업/청년",
    "industry": "",
    "budget": "",
    "benefit_type": "지원사업",
    "deadline": "경상남도",
    "link": "https://www.bizinfo.go.kr/view.do?pblancId=PBLN_000000000116174",
    "summary": "",
    "keywords": ""
  },
  {
    "source": "기업마당",
    "title": "2026년 키즈스크린 서밋(Kidscreen Summit) 한국공동관 참가기업 모집 공고",
    "region": "2026년 키즈스크린 서밋(Kidscreen Summit) 한국공동관 참가기업 모집 공고",
    "target": "중소기업/청년",
    "industry": "",
    "budget": "",
    "benefit_type": "지원사업",
    "deadline": "문화체육관광부",
    "link": "https://www.bizinfo.go.kr/view.do?pblancId=PBLN_000000000116173",
    "summary": "",
    "keywords": ""
  },
  {
    "source": "기업마당",
    "title": "2025년 에듀테크 소프트랩 우수 실증사례 및 공모전 공고",
    "region": "2025년 에듀테크 소프트랩 우수 실증사례 및 공모전 공고",
    "target": "중소기업/청년",
    "industry": "",
    "budget": "",
    "benefit_type": "지원사업",
    "deadline": "교육부",
    "link": "https://www.bizinfo.go.kr/view.do?pblancId=PBLN_000000000116172",
    "summary": "",
    "keywords": ""
  },
  {
    "source": "기업마당",
    "title": "2025년 제4차 과학기술분야 연구기획과제 공모",
    "region": "2025년 제4차 과학기술분야 연구기획과제 공모",
    "target": "중소기업/청년",
    "industry": "",
    "budget": "",
    "benefit_type": "지원사업",
    "deadline": "과학기술정보통신부",
    "link": "https://www.bizinfo.go.kr/view.do?pblancId=PBLN_000000000116171",
    "summary": "",
    "keywords": ""
  },
  {
    "source": "기업마당",
    "title": "2025년 KoDATA 오픈이노베이션 지원사업 참여 스타트업 모집 공고",
    "region": "2025년 KoDATA 오픈이노베이션 지원사업 참여 스타트업 모집 공고",
    "target": "중소기업/청년",
    "industry": "",
    "budget": "",
    "benefit_type": "지원사업",
    "deadline": "대구광역시",
    "link": "https://www.bizinfo.go.kr/view.do?pblancId=PBLN_000000000116157",
    "summary": "",
    "keywords": ""
  },
  {
    "source": "기업마당",
    "title": "[인천] 옹진군 2026년 청년어촌정착 지원사업 신청 공고",
    "region": "[인천] 옹진군 2026년 청년어촌정착 지원사업 신청 공고",
    "target": "중소기업/청년",
    "industry": "",
    "budget": "",
    "benefit_type": "지원사업",
    "deadline": "인천광역시",
    "link": "https://www.bizinfo.go.kr/view.do?pblancId=PBLN_000000000116170",
    "summary": "",
    "keywords": ""
  }
]